odoo/addons/purchase_requisition_operating_unit/README.rst
odoo/addons/purchase_requisition_operating_unit/__init__.py
odoo/addons/purchase_requisition_operating_unit/__manifest__.py
odoo/addons/purchase_requisition_operating_unit/i18n/es.po
odoo/addons/purchase_requisition_operating_unit/i18n/purchase_requisition_operating_unit.pot
odoo/addons/purchase_requisition_operating_unit/model/__init__.py
odoo/addons/purchase_requisition_operating_unit/model/purchase.py
odoo/addons/purchase_requisition_operating_unit/model/purchase_requisition.py
odoo/addons/purchase_requisition_operating_unit/readme/CONTRIBUTORS.rst
odoo/addons/purchase_requisition_operating_unit/readme/DESCRIPTION.rst
odoo/addons/purchase_requisition_operating_unit/security/purchase_security.xml
odoo/addons/purchase_requisition_operating_unit/static/description/icon.png
odoo/addons/purchase_requisition_operating_unit/static/description/index.html
odoo/addons/purchase_requisition_operating_unit/tests/__init__.py
odoo/addons/purchase_requisition_operating_unit/tests/test_purchase_requisition_operating_unit.py
odoo/addons/purchase_requisition_operating_unit/view/purchase_requisition.xml
odoo_addon_purchase_requisition_operating_unit-15.0.1.0.0.5.dist-info/METADATA
odoo_addon_purchase_requisition_operating_unit-15.0.1.0.0.5.dist-info/WHEEL
odoo_addon_purchase_requisition_operating_unit-15.0.1.0.0.5.dist-info/top_level.txt
odoo_addon_purchase_requisition_operating_unit-15.0.1.0.0.5.dist-info/RECORD
